README.txt
setup.py
Note_class/__init__.py
Note_class/note_class.py
note_class.egg-info/PKG-INFO
note_class.egg-info/SOURCES.txt
note_class.egg-info/dependency_links.txt
note_class.egg-info/requires.txt
note_class.egg-info/top_level.txt