Metadata-Version: 1.0
Name: note-class
Version: 0.1
Summary: Note Class
Home-page: https://www.test.com
Author: EranArtzi
Author-email: eartzi@gmail.com
License: UNKNOWN
Platform: UNKNOWN
